[
    {
        "id":1,
        "title": "Video 1",
        "size": "12 MB",
        "details": "",
        "created": "3 days ago.",
        "duration": "00:30:01"
    },
    {
        "id": 2,
        "title": "Video 2",
        "size": "9 MB",
        "details": "",
        "created": "2 days ago.",
        "duration": "00:23:01"
    },
    {
        "id": 3,
        "title": "Video 3",
        "size": "21 MB",
        "details": "",
        "created": "1 day ago.",
        "duration": "01:30:01"
    },
    {
        "id":4,
        "title": "Video 4",
        "size": "5 MB",
        "details": "",
        "created": "7 days ago.",
        "duration": "00:30:01"
    }
]
